{
  "type": "FeatureCollection",
  "features": [
    {
      "type": "Feature",
      "properties": { "name": "France" },
      "geometry": {
        "type": "Polygon",
        "coordinates": [[
          [-1.79, 43.42], [-1.25, 43.06], [0.70, 42.85], [1.72, 42.50],
          [3.03, 42.45], [3.21, 42.98], [4.23, 43.46], [4.94, 43.38],
          [6.15, 43.06], [6.86, 43.72], [7.38, 43.76], [7.70, 44.14],
          [6.63, 45.11], [7.14, 45.88], [6.80, 46.40], [6.05, 46.42],
          [6.15, 46.93], [5.97, 47.30], [6.69, 47.51], [7.59, 47.58],
          [8.23, 47.62], [7.42, 48.14], [7.77, 48.97], [8.22, 49.00],
          [7.45, 49.18], [6.74, 49.16], [6.36, 49.46], [5.78, 49.55],
          [4.87, 49.79], [4.45, 49.94], [4.15, 49.97], [3.59, 50.38],
          [2.54, 51.09], [1.60, 50.95], [1.42, 50.06], [0.19, 49.70],
          [-0.79, 49.35], [-1.14, 49.36], [-1.26, 49.68], [-1.79, 49.71],
          [-1.90, 48.69], [-1.04, 48.51], [-1.75, 48.12], [-1.62, 47.65],
          [-2.50, 47.52], [-2.79, 47.62], [-3.15, 47.69], [-4.32, 47.79],
          [-4.79, 48.04], [-4.55, 48.34], [-4.77, 48.53], [-4.35, 48.66],
          [-4.46, 48.86], [-3.17, 48.80], [-2.69, 48.54], [-2.00, 48.65],
          [-1.57, 48.63], [-1.90, 48.69], [-1.79, 49.71], [-1.26, 49.68],
          [-1.14, 49.36], [-1.79, 49.23], [-1.85, 48.95], [-1.35, 48.60],
          [-1.57, 48.04], [-1.02, 47.60], [-0.54, 47.52], [-0.79, 47.00],
          [-1.11, 46.31], [-1.77, 46.15], [-1.23, 45.82], [-1.15, 45.46],
          [-1.08, 45.03], [-1.19, 44.70], [-1.25, 44.47], [-1.07, 44.05],
          [-1.79, 43.42]
        ]]
      }
    },
    {
      "type": "Feature",
      "properties": { "name": "United Kingdom" },
      "geometry": {
        "type": "MultiPolygon",
        "coordinates": [
          [[
            [-5.66, 50.04], [-5.27, 50.06], [-4.77, 50.31], [-4.19, 50.37],
            [-3.68, 50.23], [-3.11, 50.42], [-2.64, 50.49], [-2.00, 50.60],
            [-1.35, 50.77], [-0.75, 50.77], [0.00, 50.78], [0.96, 50.93],
            [1.36, 51.18], [1.42, 51.38], [0.94, 51.52], [0.69, 51.47],
            [0.41, 51.45], [0.23, 51.49], [0.69, 51.71], [0.21, 52.03],
            [0.56, 52.27], [0.29, 52.45], [0.55, 52.96], [0.17, 52.94],
            [-0.19, 53.06], [0.09, 53.51], [-0.19, 53.71], [-0.29, 54.00],
            [-0.08, 54.51], [-0.79, 54.55], [-1.17, 54.64], [-1.59, 55.07],
            [-1.63, 55.58], [-1.75, 55.62], [-2.22, 56.08], [-2.06, 56.70],
            [-2.67, 56.82], [-3.35, 56.99], [-2.87, 57.71], [-3.32, 58.33],
            [-3.06, 58.45], [-4.03, 57.85], [-4.22, 57.52], [-5.64, 57.23],
            [-5.62, 56.53], [-6.15, 56.79], [-6.26, 56.21], [-5.69, 55.67],
            [-5.17, 55.45], [-4.67, 55.50], [-4.89, 54.85], [-4.96, 54.68],
            [-4.68, 54.49], [-3.62, 54.51], [-3.11, 54.10], [-3.67, 53.80],
            [-3.08, 53.40], [-2.93, 53.31], [-3.02, 53.05], [-2.68, 52.96],
            [-3.23, 52.48], [-4.15, 52.31], [-4.12, 52.91], [-4.70, 52.80],
            [-4.55, 52.57], [-4.09, 52.31], [-4.20, 51.95], [-5.00, 51.71],
            [-5.27, 51.99], [-4.25, 51.69], [-3.94, 51.61], [-3.17, 51.39],
            [-2.93, 51.52], [-3.43, 51.18], [-5.00, 51.21], [-5.19, 50.35],
            [-5.66, 50.04]
          ]]
        ]
      }
    },
    {
      "type": "Feature",
      "properties": { "name": "Belgium" },
      "geometry": {
        "type": "Polygon",
        "coordinates": [[
          [2.54, 51.09], [3.35, 51.38], [3.90, 51.21], [4.24, 51.35],
          [4.50, 51.47], [5.04, 51.49], [5.81, 51.14], [5.94, 50.75],
          [6.01, 50.13], [5.78, 49.55], [5.47, 49.50], [4.87, 49.79],
          [4.45, 49.94], [4.15, 49.97], [3.59, 50.38], [2.54, 51.09]
        ]]
      }
    },
    {
      "type": "Feature",
      "properties": { "name": "Netherlands" },
      "geometry": {
        "type": "Polygon",
        "coordinates": [[
          [3.35, 51.38], [3.83, 51.62], [4.22, 51.95], [3.44, 52.20],
          [4.28, 52.38], [4.55, 52.46], [4.72, 52.96], [4.52, 53.20],
          [5.55, 53.44], [6.09, 53.51], [6.90, 53.48], [7.09, 53.24],
          [7.21, 52.24], [7.03, 52.24], [6.75, 51.90], [5.94, 51.85],
          [5.99, 51.46], [5.81, 51.14], [5.04, 51.49], [4.50, 51.47],
          [4.24, 51.35], [3.90, 51.21], [3.35, 51.38]
        ]]
      }
    },
    {
      "type": "Feature",
      "properties": { "name": "Germany" },
      "geometry": {
        "type": "Polygon",
        "coordinates": [[
          [5.94, 50.75], [5.99, 51.46], [5.94, 51.85], [6.75, 51.90],
          [7.03, 52.24], [7.21, 52.24], [7.09, 53.24], [6.90, 53.48],
          [7.29, 53.70], [8.12, 53.87], [8.62, 54.02], [8.90, 54.28],
          [8.67, 54.87], [9.44, 54.84], [10.00, 54.67], [10.94, 54.01],
          [11.96, 54.20], [12.53, 54.47], [13.14, 54.32], [14.15, 53.93],
          [14.41, 53.28], [14.22, 52.98], [14.61, 52.57], [14.57, 51.80],
          [14.97, 51.08], [14.81, 50.86], [14.31, 50.88], [12.94, 50.42],
          [12.10, 50.30], [12.35, 49.98], [12.52, 49.55], [13.03, 49.31],
          [13.60, 48.88], [13.80, 48.77], [12.76, 48.12], [13.02, 47.64],
          [12.93, 47.47], [11.43, 47.52], [10.45, 47.56], [9.58, 47.53],
          [8.57, 47.81], [8.57, 47.60], [7.70, 47.54], [7.59, 47.58],
          [6.69, 47.51], [5.97, 47.30], [6.15, 46.93], [6.05, 46.42],
          [6.80, 46.40], [7.14, 45.88], [6.63, 45.11], [6.12, 46.24],
          [6.00, 46.42], [5.97, 47.30], [6.69, 47.51], [7.59, 47.58],
          [8.23, 47.62], [7.42, 48.14], [7.77, 48.97], [8.22, 49.00],
          [7.45, 49.18], [6.74, 49.16], [6.36, 49.46], [5.78, 49.55],
          [6.01, 50.13], [5.94, 50.75]
        ]]
      }
    },
    {
      "type": "Feature",
      "properties": { "name": "Luxembourg" },
      "geometry": {
        "type": "Polygon",
        "coordinates": [[
          [5.78, 49.55], [6.36, 49.46], [6.53, 49.80], [6.01, 50.13],
          [5.78, 49.55]
        ]]
      }
    },
    {
      "type": "Feature",
      "properties": { "name": "Spain" },
      "geometry": {
        "type": "Polygon",
        "coordinates": [[
          [-1.79, 43.42], [-1.07, 44.05], [-1.25, 44.47], [-1.86, 43.42],
          [-2.15, 43.33], [-3.00, 43.36], [-3.83, 43.47], [-4.54, 43.40],
          [-5.28, 43.62], [-6.21, 43.58], [-7.03, 43.55], [-7.87, 43.78],
          [-8.27, 43.67], [-8.89, 43.32], [-8.87, 42.61], [-9.03, 42.00],
          [-8.88, 41.86], [-8.68, 42.13], [-8.16, 41.82], [-7.51, 41.84],
          [-7.02, 41.95], [-6.56, 41.93], [-6.21, 41.57], [-6.93, 41.02],
          [-6.85, 40.00], [-7.03, 39.67], [-7.50, 39.66], [-7.14, 38.81],
          [-7.35, 38.11], [-6.88, 38.01], [-7.39, 37.78], [-7.44, 37.24],
          [-6.94, 36.98], [-6.39, 36.81], [-6.05, 36.67], [-5.44, 36.15],
          [-5.18, 36.42], [-4.33, 36.68], [-3.77, 36.74], [-2.84, 36.75],
          [-2.44, 36.84], [-1.77, 37.17], [-1.60, 37.38], [-0.82, 37.57],
          [-0.72, 37.87], [-0.63, 38.15], [0.20, 38.76], [-0.30, 39.32],
          [0.11, 39.89], [0.36, 40.34], [0.21, 40.67], [0.72, 40.80],
          [0.75, 41.15], [1.18, 41.40], [1.43, 42.05], [1.72, 42.50],
          [0.70, 42.85], [-1.25, 43.06], [-1.79, 43.42]
        ]]
      }
    },
    {
      "type": "Feature",
      "properties": { "name": "Switzerland" },
      "geometry": {
        "type": "Polygon",
        "coordinates": [[
          [6.05, 46.42], [6.80, 46.40], [7.14, 45.88], [7.44, 45.93],
          [8.42, 46.47], [9.02, 45.84], [9.26, 46.48], [9.94, 46.93],
          [10.45, 46.86], [10.45, 47.56], [9.58, 47.53], [8.57, 47.81],
          [8.57, 47.60], [7.70, 47.54], [7.59, 47.58], [6.69, 47.51],
          [5.97, 47.30], [6.15, 46.93], [6.05, 46.42]
        ]]
      }
    },
    {
      "type": "Feature",
      "properties": { "name": "Italy" },
      "geometry": {
        "type": "Polygon",
        "coordinates": [[
          [6.63, 45.11], [7.70, 44.14], [7.53, 43.78], [9.52, 43.20],
          [10.06, 43.98], [9.99, 44.07], [11.06, 45.00], [11.89, 44.99],
          [12.51, 44.97], [13.63, 45.08], [13.84, 45.60], [13.72, 46.02],
          [13.40, 46.32], [12.47, 46.68], [11.17, 46.93], [10.45, 46.86],
          [9.94, 46.93], [9.26, 46.48], [9.02, 45.84], [8.42, 46.47],
          [7.44, 45.93], [7.14, 45.88], [6.63, 45.11]
        ]]
      }
    },
    {
      "type": "Feature",
      "properties": { "name": "Ireland" },
      "geometry": {
        "type": "Polygon",
        "coordinates": [[
          [-6.20, 53.15], [-6.03, 52.93], [-6.35, 52.18], [-6.59, 52.18],
          [-7.85, 51.95], [-9.45, 51.53], [-10.25, 51.95], [-10.38, 52.22],
          [-9.68, 52.19], [-10.00, 52.49], [-10.38, 52.26], [-10.17, 52.89],
          [-9.69, 53.23], [-10.12, 53.42], [-10.02, 53.82], [-9.29, 53.74],
          [-9.62, 54.15], [-9.00, 54.22], [-8.63, 54.07], [-8.16, 54.46],
          [-7.68, 54.20], [-7.45, 54.41], [-7.71, 55.01], [-8.09, 55.11],
          [-7.56, 55.30], [-7.21, 55.09], [-6.19, 55.28], [-5.75, 54.97],
          [-5.69, 54.50], [-6.20, 53.97], [-6.22, 53.57], [-6.20, 53.15]
        ]]
      }
    }
  ]
}
